pyewt/__init__.py
pyewt/boundaries1d.py
pyewt/boundaries2d.py
pyewt/defaultparams.py
pyewt/ewt1d.py
pyewt/ewt2dcurvelet.py
pyewt/ewt2dlp.py
pyewt/ewt2dtensor.py
pyewt/ewt2dvoronoi.py
pyewt/ewt2dwatershed.py
pyewt/pseudopolarfft.py
pyewt/usefullfunc.py
pyewt-1.0.0.dist-info/METADATA
pyewt-1.0.0.dist-info/WHEEL
pyewt-1.0.0.dist-info/licenses/LICENSE
pyewt-1.0.0.dist-info/RECORD
