Metadata-Version: 2.4
Name: pyewt
Version: 1.0.0
Summary: Package implementing the Empirical Wavelet Transforms
Author-email: Jerome Gilles <jgilles@sdsu.edu>
License: MIT License
License-File: LICENSE
Keywords: analysis,empirical,harmonic analysis,image processing,mathematics,signal processing,wavelet
Classifier: Intended Audience :: Education
Classifier: Intended Audience :: Science/Research
Classifier: Operating System :: OS Independent
Classifier: Programming Language :: Python :: 3
Classifier: Topic :: Scientific/Engineering :: Image Processing
Classifier: Topic :: Scientific/Engineering :: Mathematics
Requires-Python: >=3.8
Requires-Dist: connected-components-3d
Requires-Dist: matplotlib
Requires-Dist: numpy
Requires-Dist: scikit-image
Requires-Dist: scikit-learn
Requires-Dist: scipy
